MANIFEST.in
setup.py
lychee/__init__.py
lychee/lychee.py
lychee/management.py
lychee/post.py
lychee.egg-info/PKG-INFO
lychee.egg-info/SOURCES.txt
lychee.egg-info/dependency_links.txt
lychee.egg-info/entry_points.txt
lychee.egg-info/not-zip-safe
lychee.egg-info/requires.txt
lychee.egg-info/top_level.txt
lychee/posts/2016-04-01-about.md
lychee/posts/2016-04-01-archive.md
lychee/posts/2016-04-01-index.md
lychee/posts/2016-04-01-introducing-lychee.md
lychee/static/highlight.pack.js
lychee/static/normalize.css
lychee/static/style.css
lychee/static/tomorrow.css
lychee/themes/default/about.html
lychee/themes/default/archive.html
lychee/themes/default/base.html
lychee/themes/default/index.html
lychee/themes/default/post.html