Metadata-Version: 1.0
Name: lychee
Version: 0.2.2
Summary: I'm Lychee. A static blog generator.
Home-page: UNKNOWN
Author: UNKNOWN
Author-email: UNKNOWN
License: UNKNOWN
Keywords: lychee static blog generator
Platform: UNKNOWN
